todo/__init__.py
todo/main.py
todo/utils.py
todo2-1.1.0.dist-info/DESCRIPTION.rst
todo2-1.1.0.dist-info/METADATA
todo2-1.1.0.dist-info/RECORD
todo2-1.1.0.dist-info/WHEEL
todo2-1.1.0.dist-info/entry_points.txt
todo2-1.1.0.dist-info/metadata.json
todo2-1.1.0.dist-info/top_level.txt
