Metadata-Version: 2.0
Name: todo2
Version: 1.1.0
Summary: A python todo generator.
Home-page: https://github.com/thee-engineer/todo
Author: Alexandru-Paul Copil (thee-engineer)
Author-email: alexandru.p.copil@gmail.com
License: BEERWARE
Keywords: todo
Platform: UNKNOWN
Classifier: Development Status :: 3 - Alpha
Classifier: License :: Freely Distributable
Classifier: Environment :: Console
Classifier: Intended Audience :: Developers
Classifier: Natural Language :: English
Classifier: Programming Language :: Python :: 2.7
